pyqt_distutils/__init__.py
pyqt_distutils/build_ui.py
pyqt_distutils/config.py
pyqt_distutils/hooks.py
pyqt_distutils/pyuicfg.py
pyqt_distutils/utils.py
pyqt_distutils-0.7.3.dist-info/DESCRIPTION.rst
pyqt_distutils-0.7.3.dist-info/METADATA
pyqt_distutils-0.7.3.dist-info/RECORD
pyqt_distutils-0.7.3.dist-info/WHEEL
pyqt_distutils-0.7.3.dist-info/entry_points.txt
pyqt_distutils-0.7.3.dist-info/metadata.json
pyqt_distutils-0.7.3.dist-info/top_level.txt
